{"v":4,"entries":{"component-alert--ok":{"type":"story","id":"component-alert--ok","name":"OK","title":"Component/Alert","importPath":"./src/Alert/_.stories.tsx","tags":["story"]},"component-alert--error":{"type":"story","id":"component-alert--error","name":"ERROR","title":"Component/Alert","importPath":"./src/Alert/_.stories.tsx","tags":["story"]},"component-alert--normal":{"type":"story","id":"component-alert--normal","name":"NORMAL","title":"Component/Alert","importPath":"./src/Alert/_.stories.tsx","tags":["story"]},"component-alert--warning":{"type":"story","id":"component-alert--warning","name":"WARNING","title":"Component/Alert","importPath":"./src/Alert/_.stories.tsx","tags":["story"]},"component-alerthook--index":{"type":"story","id":"component-alerthook--index","name":"Index","title":"Component/AlertHook","importPath":"./src/AlertHook/_.stories.tsx","tags":["story"]},"component-back--index":{"type":"story","id":"component-back--index","name":"Index","title":"Component/Back","importPath":"./src/Back/_.stories.tsx","tags":["story"]},"box-box--index":{"type":"story","id":"box-box--index","name":"Index","title":"Box/Box","importPath":"./src/Box/_.stories.tsx","tags":["story"]},"breadcrumb-breadcrumb--index":{"type":"story","id":"breadcrumb-breadcrumb--index","name":"Index","title":"Breadcrumb/Breadcrumb","importPath":"./src/Breadcrumb/_.stories.tsx","tags":["story"]},"component-button--index":{"type":"story","id":"component-button--index","name":"Index","title":"Component/Button","importPath":"./src/Button/_.stories.tsx","tags":["story"]},"chat-chat--primary":{"type":"story","id":"chat-chat--primary","name":"Primary","title":"Chat/Chat","importPath":"./src/Chat/Chat/_.stories.tsx","tags":["story"]},"chat-chatformsendmessage--primary":{"type":"story","id":"chat-chatformsendmessage--primary","name":"Primary","title":"Chat/ChatFormSendMessage","importPath":"./src/Chat/FormSendMessage/_.stories.tsx","tags":["story"]},"chat-message--primary":{"type":"story","id":"chat-message--primary","name":"Primary","title":"Chat/Message","importPath":"./src/Chat/Message/_.stories.tsx","tags":["story"]},"chat-user--primary":{"type":"story","id":"chat-user--primary","name":"Primary","title":"Chat/User","importPath":"./src/Chat/User/_.stories.tsx","tags":["story"]},"chronologicallist-chronologicallist--index":{"type":"story","id":"chronologicallist-chronologicallist--index","name":"Index","title":"ChronologicalList/ChronologicalList","importPath":"./src/ChronologicalList/_.stories.tsx","tags":["story"]},"chronometer-chronometer--index":{"type":"story","id":"chronometer-chronometer--index","name":"Index","title":"Chronometer/Chronometer","importPath":"./src/Chronometer/_.stories.tsx","tags":["story"]},"collapse-multiple--index":{"type":"story","id":"collapse-multiple--index","name":"Index","title":"Collapse/Multiple","importPath":"./src/Collapse/Multiple/_.stories.tsx","tags":["story"]},"collapse-simple--index":{"type":"story","id":"collapse-simple--index","name":"Index","title":"Collapse/Simple","importPath":"./src/Collapse/Simple/_.stories.tsx","tags":["story"]},"cols-cols--index":{"type":"story","id":"cols-cols--index","name":"Index","title":"Cols/Cols","importPath":"./src/Cols/_.stories.tsx","tags":["story"]},"component-container--index":{"type":"story","id":"component-container--index","name":"Index","title":"Component/Container","importPath":"./src/Container/_.stories.tsx","tags":["story"]},"contentloading-contentloading--index":{"type":"story","id":"contentloading-contentloading--index","name":"Index","title":"ContentLoading/ContentLoading","importPath":"./src/ContentLoading/_.stories.tsx","tags":["story"]},"contentshow-contentshow--index":{"type":"story","id":"contentshow-contentshow--index","name":"Index","title":"ContentShow/ContentShow","importPath":"./src/ContentShow/_.stories.tsx","tags":["story"]},"copy-copy--index":{"type":"story","id":"copy-copy--index","name":"Index","title":"Copy/Copy","importPath":"./src/Copy/_.stories.tsx","tags":["story"]},"counter-counter--index":{"type":"story","id":"counter-counter--index","name":"Index","title":"Counter/Counter","importPath":"./src/Counter/_.stories.tsx","tags":["story"]},"counter-counter--negative":{"type":"story","id":"counter-counter--negative","name":"Negative","title":"Counter/Counter","importPath":"./src/Counter/_.stories.tsx","tags":["story"]},"dropdown-dropdown--index":{"type":"story","id":"dropdown-dropdown--index","name":"Index","title":"DropDown/DropDown","importPath":"./src/DropDown/_.stories.tsx","tags":["story"]},"dropdown-dropdown--left":{"type":"story","id":"dropdown-dropdown--left","name":"Left","title":"DropDown/DropDown","importPath":"./src/DropDown/_.stories.tsx","tags":["story"]},"dropdown-dropdown--right":{"type":"story","id":"dropdown-dropdown--right","name":"Right","title":"DropDown/DropDown","importPath":"./src/DropDown/_.stories.tsx","tags":["story"]},"dropdown-dropdown--up":{"type":"story","id":"dropdown-dropdown--up","name":"Up","title":"DropDown/DropDown","importPath":"./src/DropDown/_.stories.tsx","tags":["story"]},"dropdown-dropdown--up-right":{"type":"story","id":"dropdown-dropdown--up-right","name":"Up Right","title":"DropDown/DropDown","importPath":"./src/DropDown/_.stories.tsx","tags":["story"]},"error-errorcomponent--index":{"type":"story","id":"error-errorcomponent--index","name":"Index","title":"Error/ErrorComponent","importPath":"./src/Error/_.stories.tsx","tags":["story"]},"error-errorcomponent--with-error":{"type":"story","id":"error-errorcomponent--with-error","name":"With Error","title":"Error/ErrorComponent","importPath":"./src/Error/_.stories.tsx","tags":["story"]},"component-form--index":{"type":"story","id":"component-form--index","name":"Index","title":"Component/Form","importPath":"./src/Form/_.stories.tsx","tags":["story"]},"gridgallery-gridgallery--index":{"type":"story","id":"gridgallery-gridgallery--index","name":"Index","title":"GridGallery/GridGallery","importPath":"./src/GridGallery/_.stories.tsx","tags":["story"]},"header-buttonmenu--index":{"type":"story","id":"header-buttonmenu--index","name":"Index","title":"Header/ButtonMenu","importPath":"./src/Header/ButtonMenu/_.stories.tsx","tags":["story"]},"header-itemmenu--index":{"type":"story","id":"header-itemmenu--index","name":"Index","title":"Header/ItemMenu","importPath":"./src/Header/ItemMenu/_.stories.tsx","tags":["story"]},"header-itemmenu--sub-items":{"type":"story","id":"header-itemmenu--sub-items","name":"Sub Items","title":"Header/ItemMenu","importPath":"./src/Header/ItemMenu/_.stories.tsx","tags":["story"]},"header-menu--index":{"type":"story","id":"header-menu--index","name":"Index","title":"Header/Menu","importPath":"./src/Header/Menu/_.stories.tsx","tags":["story"]},"img-img--index":{"type":"story","id":"img-img--index","name":"Index","title":"Img/Img","importPath":"./src/Img/_.stories.tsx","tags":["story"]},"img-img--with-layer":{"type":"story","id":"img-img--with-layer","name":"With Layer","title":"Img/Img","importPath":"./src/Img/_.stories.tsx","tags":["story"]},"img-imggallery--index":{"type":"story","id":"img-imggallery--index","name":"Index","title":"Img/ImgGallery","importPath":"./src/ImgGallery/_.stories.tsx","tags":["story"]},"img-imgslider--index":{"type":"story","id":"img-imgslider--index","name":"Index","title":"Img/ImgSlider","importPath":"./src/ImgSlider/_.stories.tsx","tags":["story"]},"input-inputcalendarmonth--index":{"type":"story","id":"input-inputcalendarmonth--index","name":"Index","title":"Input/InputCalendarMonth","importPath":"./src/Input/Calendar/Month/_.stories.tsx","tags":["story"]},"input-inputcalendar--index":{"type":"story","id":"input-inputcalendar--index","name":"Index","title":"Input/InputCalendar","importPath":"./src/Input/Calendar/_.stories.tsx","tags":["story"]},"input-card-inputcardccv--index":{"type":"story","id":"input-card-inputcardccv--index","name":"Index","title":"Input/Card/InputCardCCV","importPath":"./src/Input/Card/CCV/_.stories.tsx","tags":["story"]},"input-card-inputcardexpdate--index":{"type":"story","id":"input-card-inputcardexpdate--index","name":"Index","title":"Input/Card/InputCardExpDate","importPath":"./src/Input/Card/ExpDate/_.stories.tsx","tags":["story"]},"input-card-inputcardnumber--index":{"type":"story","id":"input-card-inputcardnumber--index","name":"Index","title":"Input/Card/InputCardNumber","importPath":"./src/Input/Card/Number/_.stories.tsx","tags":["story"]},"input-inputcheckbox--index":{"type":"story","id":"input-inputcheckbox--index","name":"Index","title":"Input/InputCheckbox","importPath":"./src/Input/Checkbox/_.stories.tsx","tags":["story"]},"input-inputcode--index":{"type":"story","id":"input-inputcode--index","name":"Index","title":"Input/InputCode","importPath":"./src/Input/Code/_.stories.tsx","tags":["story"]},"input-inputdate--index":{"type":"story","id":"input-inputdate--index","name":"Index","title":"Input/InputDate","importPath":"./src/Input/Date/_.stories.tsx","tags":["story"]},"input-inputdate--use-validator":{"type":"story","id":"input-inputdate--use-validator","name":"Use Validator","title":"Input/InputDate","importPath":"./src/Input/Date/_.stories.tsx","tags":["story"]},"input-inputdaterange--index":{"type":"story","id":"input-inputdaterange--index","name":"Index","title":"Input/InputDateRange","importPath":"./src/Input/DateRange/_.stories.tsx","tags":["story"]},"input-inputfile--index":{"type":"story","id":"input-inputfile--index","name":"Index","title":"Input/InputFile","importPath":"./src/Input/File/_.stories.tsx","tags":["story"]},"input-inputfilestatus--approved":{"type":"story","id":"input-inputfilestatus--approved","name":"APPROVED","title":"Input/InputFileStatus","importPath":"./src/Input/FileStatus/_.stories.tsx","tags":["story"]},"input-inputfilestatus--pending":{"type":"story","id":"input-inputfilestatus--pending","name":"PENDING","title":"Input/InputFileStatus","importPath":"./src/Input/FileStatus/_.stories.tsx","tags":["story"]},"input-inputfilestatus--rejected":{"type":"story","id":"input-inputfilestatus--rejected","name":"REJECTED","title":"Input/InputFileStatus","importPath":"./src/Input/FileStatus/_.stories.tsx","tags":["story"]},"input-inputgallery--index":{"type":"story","id":"input-inputgallery--index","name":"Index","title":"Input/InputGallery","importPath":"./src/Input/Gallery/_.stories.tsx","tags":["story"]},"input-google-autocomplete--index":{"type":"story","id":"input-google-autocomplete--index","name":"Index","title":"Input/Google/Autocomplete","importPath":"./src/Input/Google/Autocomplete/_.stories.tsx","tags":["story"]},"input-google-loadscript--index":{"type":"story","id":"input-google-loadscript--index","name":"Index","title":"Input/Google/LoadScript","importPath":"./src/Input/Google/LoadScript/_.stories.tsx","tags":["story"]},"input-google-maps--index":{"type":"story","id":"input-google-maps--index","name":"Index","title":"Input/Google/Maps","importPath":"./src/Input/Google/Maps/_.stories.tsx","tags":["story"]},"input-inputimg--index":{"type":"story","id":"input-inputimg--index","name":"Index","title":"Input/InputImg","importPath":"./src/Input/Img/_.stories.tsx","tags":["story"]},"input-inputimg--error":{"type":"story","id":"input-inputimg--error","name":"Error","title":"Input/InputImg","importPath":"./src/Input/Img/_.stories.tsx","tags":["story"]},"input-inputnumber--index":{"type":"story","id":"input-inputnumber--index","name":"Index","title":"Input/InputNumber","importPath":"./src/Input/Number/_.stories.tsx","tags":["story"]},"input-inputnumber--use-validator":{"type":"story","id":"input-inputnumber--use-validator","name":"Use Validator","title":"Input/InputNumber","importPath":"./src/Input/Number/_.stories.tsx","tags":["story"]},"input-inputnumbercount--index":{"type":"story","id":"input-inputnumbercount--index","name":"Index","title":"Input/InputNumberCount","importPath":"./src/Input/NumberCount/_.stories.tsx","tags":["story"]},"input-inputnumbercount--use-validator":{"type":"story","id":"input-inputnumbercount--use-validator","name":"Use Validator","title":"Input/InputNumberCount","importPath":"./src/Input/NumberCount/_.stories.tsx","tags":["story"]},"input-inputpassword--index":{"type":"story","id":"input-inputpassword--index","name":"Index","title":"Input/InputPassword","importPath":"./src/Input/Password/_.stories.tsx","tags":["story"]},"input-inputphone--index":{"type":"story","id":"input-inputphone--index","name":"Index","title":"Input/InputPhone","importPath":"./src/Input/Phone/_.stories.tsx","tags":["story"]},"input-inputphone--use-validator":{"type":"story","id":"input-inputphone--use-validator","name":"Use Validator","title":"Input/InputPhone","importPath":"./src/Input/Phone/_.stories.tsx","tags":["story"]},"input-inputradio--index":{"type":"story","id":"input-inputradio--index","name":"Index","title":"Input/InputRadio","importPath":"./src/Input/Radio/_.stories.tsx","tags":["story"]},"input-inputrange--index":{"type":"story","id":"input-inputrange--index","name":"Index","title":"Input/InputRange","importPath":"./src/Input/Range/_.stories.tsx","tags":["story"]},"input-inputrate--index":{"type":"story","id":"input-inputrate--index","name":"Index","title":"Input/InputRate","importPath":"./src/Input/Rate/_.stories.tsx","tags":["story"]},"input-scanner-inputscannerqr--index":{"type":"story","id":"input-scanner-inputscannerqr--index","name":"Index","title":"Input/Scanner/InputScannerQr","importPath":"./src/Input/Scanner/Qr/_.stories.tsx","tags":["story"]},"input-scanner-inputscannertextqr--index":{"type":"story","id":"input-scanner-inputscannertextqr--index","name":"Index","title":"Input/Scanner/InputScannerTextQr","importPath":"./src/Input/Scanner/TextQr/_.stories.tsx","tags":["story"]},"input-inputsearch--index":{"type":"story","id":"input-inputsearch--index","name":"Index","title":"Input/InputSearch","importPath":"./src/Input/Search/_.stories.tsx","tags":["story"]},"input-inputselect--index":{"type":"story","id":"input-inputselect--index","name":"Index","title":"Input/InputSelect","importPath":"./src/Input/Select/_.stories.tsx","tags":["story"]},"input-inputselect--with-validator":{"type":"story","id":"input-inputselect--with-validator","name":"With Validator","title":"Input/InputSelect","importPath":"./src/Input/Select/_.stories.tsx","tags":["story"]},"input-inputselect--in-oveflow":{"type":"story","id":"input-inputselect--in-oveflow","name":"In Oveflow","title":"Input/InputSelect","importPath":"./src/Input/Select/_.stories.tsx","tags":["story"]},"input-inputselect--testing-select-movil-in-modal":{"type":"story","id":"input-inputselect--testing-select-movil-in-modal","name":"Testing Select Movil In Modal","title":"Input/InputSelect","importPath":"./src/Input/Select/_.stories.tsx","tags":["story"]},"input-inputselect--in-layout":{"type":"story","id":"input-inputselect--in-layout","name":"In Layout","title":"Input/InputSelect","importPath":"./src/Input/Select/_.stories.tsx","tags":["story"]},"input-inputselect--box":{"type":"story","id":"input-inputselect--box","name":"Box","title":"Input/InputSelect","importPath":"./src/Input/Select/_.stories.tsx","tags":["story"]},"input-inputselect--checkbox":{"type":"story","id":"input-inputselect--checkbox","name":"Checkbox","title":"Input/InputSelect","importPath":"./src/Input/Select/_.stories.tsx","tags":["story"]},"input-inputselect--max-length-options":{"type":"story","id":"input-inputselect--max-length-options","name":"Max Length Options","title":"Input/InputSelect","importPath":"./src/Input/Select/_.stories.tsx","tags":["story"]},"input-inputselect--validator-data":{"type":"story","id":"input-inputselect--validator-data","name":"Validator Data","title":"Input/InputSelect","importPath":"./src/Input/Select/_.stories.tsx","tags":["story"]},"input-inputselect--with-loader":{"type":"story","id":"input-inputselect--with-loader","name":"With Loader","title":"Input/InputSelect","importPath":"./src/Input/Select/_.stories.tsx","tags":["story"]},"input-inputselectcsc--index":{"type":"story","id":"input-inputselectcsc--index","name":"Index","title":"Input/InputSelectCSC","importPath":"./src/Input/SelectCSC/_.stories.tsx","tags":["story"]},"input-inputselectcity--index":{"type":"story","id":"input-inputselectcity--index","name":"Index","title":"Input/InputSelectCity","importPath":"./src/Input/SelectCity/_.stories.tsx","tags":["story"]},"input-inputselectcountry--index":{"type":"story","id":"input-inputselectcountry--index","name":"Index","title":"Input/InputSelectCountry","importPath":"./src/Input/SelectCountry/_.stories.tsx","tags":["story"]},"input-inputselectcountrymultiple--index":{"type":"story","id":"input-inputselectcountrymultiple--index","name":"Index","title":"Input/InputSelectCountryMultiple","importPath":"./src/Input/SelectCountryMultiple/_.stories.tsx","tags":["story"]},"input-inputselectmultiple--index":{"type":"story","id":"input-inputselectmultiple--index","name":"Index","title":"Input/InputSelectMultiple","importPath":"./src/Input/SelectMultiple/_.stories.tsx","tags":["story"]},"input-inputselectmultiple--custom-options-selected":{"type":"story","id":"input-inputselectmultiple--custom-options-selected","name":"Custom Options Selected","title":"Input/InputSelectMultiple","importPath":"./src/Input/SelectMultiple/_.stories.tsx","tags":["story"]},"input-inputselectnumber--index":{"type":"story","id":"input-inputselectnumber--index","name":"Index","title":"Input/InputSelectNumber","importPath":"./src/Input/SelectNumber/_.stories.tsx","tags":["story"]},"input-inputselectnumber--use-validator":{"type":"story","id":"input-inputselectnumber--use-validator","name":"Use Validator","title":"Input/InputSelectNumber","importPath":"./src/Input/SelectNumber/_.stories.tsx","tags":["story"]},"input-inputselectoption--index":{"type":"story","id":"input-inputselectoption--index","name":"Index","title":"Input/InputSelectOption","importPath":"./src/Input/SelectOption/_.stories.tsx","tags":["story"]},"input-inputselectstate--index":{"type":"story","id":"input-inputselectstate--index","name":"Index","title":"Input/InputSelectState","importPath":"./src/Input/SelectState/_.stories.tsx","tags":["story"]},"input-inputselectt--index":{"type":"story","id":"input-inputselectt--index","name":"Index","title":"Input/InputSelectT","importPath":"./src/Input/SelectT/_.stories.tsx","tags":["story"]},"input-inputselecttimezone--index":{"type":"story","id":"input-inputselecttimezone--index","name":"Index","title":"Input/InputSelectTimeZone","importPath":"./src/Input/SelectTimeZone/_.stories.tsx","tags":["story"]},"input-inputswich--index":{"type":"story","id":"input-inputswich--index","name":"Index","title":"Input/InputSwich","importPath":"./src/Input/Swich/_.stories.tsx","tags":["story"]},"input-inputtext--index":{"type":"story","id":"input-inputtext--index","name":"Index","title":"Input/InputText","importPath":"./src/Input/Text/_.stories.tsx","tags":["story"]},"input-inputtext--use-validator":{"type":"story","id":"input-inputtext--use-validator","name":"Use Validator","title":"Input/InputText","importPath":"./src/Input/Text/_.stories.tsx","tags":["story"]},"input-inputtextselect--index":{"type":"story","id":"input-inputtextselect--index","name":"Index","title":"Input/InputTextSelect","importPath":"./src/Input/TextSelect/_.stories.tsx","tags":["story"]},"input-inputunitbase--index":{"type":"story","id":"input-inputunitbase--index","name":"Index","title":"Input/InputUnitBase","importPath":"./src/Input/Unit/Base/_.stories.tsx","tags":["story"]},"input-inputunitdistance--index":{"type":"story","id":"input-inputunitdistance--index","name":"Index","title":"Input/InputUnitDistance","importPath":"./src/Input/Unit/Distance/_.stories.tsx","tags":["story"]},"input-inputunitvolumen--index":{"type":"story","id":"input-inputunitvolumen--index","name":"Index","title":"Input/InputUnitVolumen","importPath":"./src/Input/Unit/Volumen/_.stories.tsx","tags":["story"]},"input-inputunitweight--index":{"type":"story","id":"input-inputunitweight--index","name":"Index","title":"Input/InputUnitWeight","importPath":"./src/Input/Unit/Weight/_.stories.tsx","tags":["story"]},"input-inputupload--index":{"type":"story","id":"input-inputupload--index","name":"Index","title":"Input/InputUpload","importPath":"./src/Input/Upload/_.stories.tsx","tags":["story"]},"input-inputupload--error":{"type":"story","id":"input-inputupload--error","name":"Error","title":"Input/InputUpload","importPath":"./src/Input/Upload/_.stories.tsx","tags":["story"]},"input-inputupload--custom-preview":{"type":"story","id":"input-inputupload--custom-preview","name":"Custom Preview","title":"Input/InputUpload","importPath":"./src/Input/Upload/_.stories.tsx","tags":["story"]},"lavalamp-lavalamp--index":{"type":"story","id":"lavalamp-lavalamp--index","name":"Index","title":"LavaLamp/LavaLamp","importPath":"./src/LavaLamp/_.stories.tsx","tags":["story"]},"layout-layoutgridmenuleft--index":{"type":"story","id":"layout-layoutgridmenuleft--index","name":"Index","title":"Layout/LayoutGridMenuLeft","importPath":"./src/Layout/Grid/GridMenuLeft/_.stories.tsx","tags":["story"]},"layout-layoutgridmenuleft--with-btn-menu":{"type":"story","id":"layout-layoutgridmenuleft--with-btn-menu","name":"With Btn Menu","title":"Layout/LayoutGridMenuLeft","importPath":"./src/Layout/Grid/GridMenuLeft/_.stories.tsx","tags":["story"]},"layout-layoutgridmenutop--index":{"type":"story","id":"layout-layoutgridmenutop--index","name":"Index","title":"Layout/LayoutGridMenuTop","importPath":"./src/Layout/Grid/GridMenuTop/_.stories.tsx","tags":["story"]},"layout-layoutgridmenutopleft--index":{"type":"story","id":"layout-layoutgridmenutopleft--index","name":"Index","title":"Layout/LayoutGridMenuTopLeft","importPath":"./src/Layout/Grid/GridMenuTopLeft/_.stories.tsx","tags":["story"]},"layout-layoutgridmenutopleft--with-btn-menu":{"type":"story","id":"layout-layoutgridmenutopleft--with-btn-menu","name":"With Btn Menu","title":"Layout/LayoutGridMenuTopLeft","importPath":"./src/Layout/Grid/GridMenuTopLeft/_.stories.tsx","tags":["story"]},"layout-layoutgridmenutopleft--with-btn-menu-and-element-container":{"type":"story","id":"layout-layoutgridmenutopleft--with-btn-menu-and-element-container","name":"With Btn Menu And Element Container","title":"Layout/LayoutGridMenuTopLeft","importPath":"./src/Layout/Grid/GridMenuTopLeft/_.stories.tsx","tags":["story"]},"component-link--index":{"type":"story","id":"component-link--index","name":"Index","title":"Component/Link","importPath":"./src/Link/_.stories.tsx","tags":["story"]},"loader-loader--index":{"type":"story","id":"loader-loader--index","name":"Index","title":"Loader/Loader","importPath":"./src/Loader/Current/_.stories.tsx","tags":["story"]},"loader-line--index":{"type":"story","id":"loader-line--index","name":"Index","title":"Loader/Line","importPath":"./src/Loader/Line/_.stories.tsx","tags":["story"]},"loader-spinner--index":{"type":"story","id":"loader-spinner--index","name":"Index","title":"Loader/Spinner","importPath":"./src/Loader/Spinner/_.stories.tsx","tags":["story"]},"loader-user--index":{"type":"story","id":"loader-user--index","name":"Index","title":"Loader/User","importPath":"./src/Loader/User/_.stories.tsx","tags":["story"]},"media-input--index":{"type":"story","id":"media-input--index","name":"Index","title":"Media/Input","importPath":"./src/Media/Input/_.stories.tsx","tags":["story"]},"media-page--index":{"type":"story","id":"media-page--index","name":"Index","title":"Media/Page","importPath":"./src/Media/Page/_.stories.tsx","tags":["story"]},"modal-modalbase--index":{"type":"story","id":"modal-modalbase--index","name":"Index","title":"Modal/ModalBase","importPath":"./src/Modal/Base/_.stories.tsx","tags":["story"]},"modal-modal--index":{"type":"story","id":"modal-modal--index","name":"Index","title":"Modal/Modal","importPath":"./src/Modal/Modal/_.stories.tsx","tags":["story"]},"modal-modal--with-layout":{"type":"story","id":"modal-modal--with-layout","name":"With Layout","title":"Modal/Modal","importPath":"./src/Modal/Modal/_.stories.tsx","tags":["story"]},"modal-modal--modal-in-modal":{"type":"story","id":"modal-modal--modal-in-modal","name":"Modal In Modal","title":"Modal/Modal","importPath":"./src/Modal/Modal/_.stories.tsx","tags":["story"]},"modal-modal--btn-use-modal-name":{"type":"story","id":"modal-modal--btn-use-modal-name","name":"Btn Use Modal Name","title":"Modal/Modal","importPath":"./src/Modal/Modal/_.stories.tsx","tags":["story"]},"modal-modal--use-modal-name":{"type":"story","id":"modal-modal--use-modal-name","name":"Use Modal Name","title":"Modal/Modal","importPath":"./src/Modal/Modal/_.stories.tsx","tags":["story"]},"notification-notification--index":{"type":"story","id":"notification-notification--index","name":"Index","title":"Notification/Notification","importPath":"./src/Notification/Fixed/_.stories.tsx","tags":["story"]},"notification-notification--error":{"type":"story","id":"notification-notification--error","name":"ERROR","title":"Notification/Notification","importPath":"./src/Notification/Fixed/_.stories.tsx","tags":["story"]},"notification-notification--ok":{"type":"story","id":"notification-notification--ok","name":"OK","title":"Notification/Notification","importPath":"./src/Notification/Fixed/_.stories.tsx","tags":["story"]},"notification-notification--warning":{"type":"story","id":"notification-notification--warning","name":"WARNING","title":"Notification/Notification","importPath":"./src/Notification/Fixed/_.stories.tsx","tags":["story"]},"notification-notificationpop--index":{"type":"story","id":"notification-notificationpop--index","name":"Index","title":"Notification/NotificationPop","importPath":"./src/Notification/Pop/_.stories.tsx","tags":["story"]},"pageprogress-pageprogress--index":{"type":"story","id":"pageprogress-pageprogress--index","name":"Index","title":"PageProgress/PageProgress","importPath":"./src/PageProgress/_.stories.tsx","tags":["story"]},"pagination-pagination--index":{"type":"story","id":"pagination-pagination--index","name":"Index","title":"Pagination/Pagination","importPath":"./src/Pagination/PaginationAll/_.stories.tsx","tags":["story"]},"pagination-paginationitempage--index":{"type":"story","id":"pagination-paginationitempage--index","name":"Index","title":"Pagination/PaginationItemPage","importPath":"./src/Pagination/PaginationItemPage/_.stories.tsx","tags":["story"]},"pagination-paginationnpage--index":{"type":"story","id":"pagination-paginationnpage--index","name":"Index","title":"Pagination/PaginationNPage","importPath":"./src/Pagination/PaginationNPage/_.stories.tsx","tags":["story"]},"print-iframe--index":{"type":"story","id":"print-iframe--index","name":"Index","title":"Print/Iframe","importPath":"./src/Print/Iframe/_.stories.tsx","tags":["story"]},"print-page--index":{"type":"story","id":"print-page--index","name":"Index","title":"Print/Page","importPath":"./src/Print/Page/_.stories.tsx","tags":["story"]},"progress-progresscircle--index":{"type":"story","id":"progress-progresscircle--index","name":"Index","title":"Progress/ProgressCircle","importPath":"./src/Progress/Circle/_.stories.tsx","tags":["story"]},"progress-progressline--index":{"type":"story","id":"progress-progressline--index","name":"Index","title":"Progress/ProgressLine","importPath":"./src/Progress/Line/_.stories.tsx","tags":["story"]},"schedule-scheduleday--index":{"type":"story","id":"schedule-scheduleday--index","name":"Index","title":"Schedule/ScheduleDay","importPath":"./src/Schedule/Day/_.stories.tsx","tags":["story"]},"schedule-scheduleweekly--index":{"type":"story","id":"schedule-scheduleweekly--index","name":"Index","title":"Schedule/ScheduleWeekly","importPath":"./src/Schedule/Weekly/_.stories.tsx","tags":["story"]},"share-share--index":{"type":"story","id":"share-share--index","name":"Index","title":"Share/Share","importPath":"./src/Share/_.stories.tsx","tags":["story"]},"slider-slider--index":{"type":"story","id":"slider-slider--index","name":"Index","title":"Slider/Slider","importPath":"./src/Slider/_.stories.tsx","tags":["story"]},"steps-steps--index":{"type":"story","id":"steps-steps--index","name":"Index","title":"Steps/Steps","importPath":"./src/Steps/_.stories.tsx","tags":["story"]},"steps-steps--use-step":{"type":"story","id":"steps-steps--use-step","name":"Use Step","title":"Steps/Steps","importPath":"./src/Steps/_.stories.tsx","tags":["story"]},"swichview-list--index":{"type":"story","id":"swichview-list--index","name":"Index","title":"SwichView/List","importPath":"./src/SwichView/SwichViewList/_.stories.tsx","tags":["story"]},"swichview-select--index":{"type":"story","id":"swichview-select--index","name":"Index","title":"SwichView/Select","importPath":"./src/SwichView/SwichViewSelect/_.stories.tsx","tags":["story"]},"swichview-select--interna":{"type":"story","id":"swichview-select--interna","name":"Interna","title":"SwichView/Select","importPath":"./src/SwichView/SwichViewSelect/_.stories.tsx","tags":["story"]},"swichview-select--multiple":{"type":"story","id":"swichview-select--multiple","name":"Multiple","title":"SwichView/Select","importPath":"./src/SwichView/SwichViewSelect/_.stories.tsx","tags":["story"]},"swichview-table--index":{"type":"story","id":"swichview-table--index","name":"Index","title":"SwichView/Table","importPath":"./src/SwichView/SwichViewTable/_.stories.tsx","tags":["story"]},"component-tab--index":{"type":"story","id":"component-tab--index","name":"Index","title":"Component/Tab","importPath":"./src/Tab/_.stories.tsx","tags":["story"]},"component-tab--one-tab":{"type":"story","id":"component-tab--one-tab","name":"One Tab","title":"Component/Tab","importPath":"./src/Tab/_.stories.tsx","tags":["story"]},"table-table--index":{"type":"story","id":"table-table--index","name":"Index","title":"Table/Table","importPath":"./src/Table/_.stories.tsx","tags":["story"]},"table-table--one-item":{"type":"story","id":"table-table--one-item","name":"One Item","title":"Table/Table","importPath":"./src/Table/_.stories.tsx","tags":["story"]},"table-table--not-item":{"type":"story","id":"table-table--not-item","name":"Not Item","title":"Table/Table","importPath":"./src/Table/_.stories.tsx","tags":["story"]},"table-table--table-in-table":{"type":"story","id":"table-table--table-in-table","name":"Table In Table","title":"Table/Table","importPath":"./src/Table/_.stories.tsx","tags":["story"]},"table-table--actions":{"type":"story","id":"table-table--actions","name":"Actions","title":"Table/Table","importPath":"./src/Table/_.stories.tsx","tags":["story"]},"table-tableactioncheckbox--index":{"type":"story","id":"table-tableactioncheckbox--index","name":"Index","title":"Table/TableActionCheckbox","importPath":"./src/TableActionCheckbox/_.stories.tsx","tags":["story"]},"template-template--index":{"type":"story","id":"template-template--index","name":"Index","title":"Template/Template","importPath":"./src/Template/_.stories.tsx","tags":["story"]},"text-text--index":{"type":"story","id":"text-text--index","name":"Index","title":"Text/Text","importPath":"./src/Text/_.stories.tsx","tags":["story"]},"theme-theme--index":{"type":"story","id":"theme-theme--index","name":"Index","title":"Theme/Theme","importPath":"./src/Theme/_.stories.tsx","tags":["story"]},"title-title--h-1":{"type":"story","id":"title-title--h-1","name":"H 1","title":"Title/Title","importPath":"./src/Title/_.stories.tsx","tags":["story"]},"title-title--h-2":{"type":"story","id":"title-title--h-2","name":"H 2","title":"Title/Title","importPath":"./src/Title/_.stories.tsx","tags":["story"]},"title-title--h-3":{"type":"story","id":"title-title--h-3","name":"H 3","title":"Title/Title","importPath":"./src/Title/_.stories.tsx","tags":["story"]},"title-title--h-4":{"type":"story","id":"title-title--h-4","name":"H 4","title":"Title/Title","importPath":"./src/Title/_.stories.tsx","tags":["story"]},"title-title--h-5":{"type":"story","id":"title-title--h-5","name":"H 5","title":"Title/Title","importPath":"./src/Title/_.stories.tsx","tags":["story"]},"title-title--h-6":{"type":"story","id":"title-title--h-6","name":"H 6","title":"Title/Title","importPath":"./src/Title/_.stories.tsx","tags":["story"]},"tooltip-tooltip--index":{"type":"story","id":"tooltip-tooltip--index","name":"Index","title":"Tooltip/Tooltip","importPath":"./src/Tooltip/_.stories.tsx","tags":["story"]},"twocolsticky-twocolsticky--index":{"type":"story","id":"twocolsticky-twocolsticky--index","name":"Index","title":"TwoColSticky/TwoColSticky","importPath":"./src/TwoColSticky/_.stories.tsx","tags":["story"]},"user-user--index":{"type":"story","id":"user-user--index","name":"Index","title":"User/User","importPath":"./src/User/_.stories.tsx","tags":["story"]},"user-user--not-img":{"type":"story","id":"user-user--not-img","name":"Not Img","title":"User/User","importPath":"./src/User/_.stories.tsx","tags":["story"]}}}
